clone_repos/__init__.py
clone_repos/__main__.py
clone_repos/py.typed
clone_repos/repo.py
cl_repos-0.1.1.dist-info/LICENSE
cl_repos-0.1.1.dist-info/METADATA
cl_repos-0.1.1.dist-info/WHEEL
cl_repos-0.1.1.dist-info/entry_points.txt
cl_repos-0.1.1.dist-info/top_level.txt
cl_repos-0.1.1.dist-info/RECORD
