Metadata-Version: 2.1
Name: cl-repos
Version: 0.1.1
Summary: a basic git repo clone script
Home-page: https://github.com/seanbreckenridge/clone_repos
Author: Sean Breckenridge
Author-email: "seanbrecke@gmail.com"
License: MIT
Keywords: git,github,clone
Classifier: License :: OSI Approved :: MIT License
Classifier: Programming Language :: Python
Classifier: Programming Language :: Python :: 3
Classifier: Programming Language :: Python :: 3 :: Only
Classifier: Programming Language :: Python :: 3.9
Classifier: Programming Language :: Python :: 3.10
Classifier: Programming Language :: Python :: 3.11
Classifier: Programming Language :: Python :: 3.12
Requires-Python: >=3.9
License-File: LICENSE
Requires-Dist: click >=8.0
Requires-Dist: pyyaml
Requires-Dist: reorder-editable
Provides-Extra: testing
Requires-Dist: flake8 ; extra == 'testing'
Requires-Dist: mypy ; extra == 'testing'
Requires-Dist: pytest ; extra == 'testing'
